setup.py
src/Hatak_Toster.egg-info/PKG-INFO
src/Hatak_Toster.egg-info/SOURCES.txt
src/Hatak_Toster.egg-info/dependency_links.txt
src/Hatak_Toster.egg-info/namespace_packages.txt
src/Hatak_Toster.egg-info/not-zip-safe
src/Hatak_Toster.egg-info/requires.txt
src/Hatak_Toster.egg-info/top_level.txt
src/haplugin/__init__.py
src/haplugin/toster/__init__.py
src/haplugin/toster/cases.py
src/haplugin/toster/commands.py
src/haplugin/toster/database.py
src/haplugin/toster/fixtures.py
src/haplugin/toster/plugin.py
src/haplugin/toster/runner.py