Metadata-Version: 1.0
Name: Hatak-Toster
Version: 0.1.3
Summary: Toster plugin for Hatak.
Home-page: UNKNOWN
Author: UNKNOWN
Author-email: UNKNOWN
License: Apache License 2.0
Platform: UNKNOWN
